LICENSE.md
MANIFEST.in
README.md
setup.py
dbt/adapters/bigquery/__init__.py
dbt/adapters/bigquery/__version__.py
dbt/adapters/bigquery/column.py
dbt/adapters/bigquery/connections.py
dbt/adapters/bigquery/gcloud.py
dbt/adapters/bigquery/impl.py
dbt/adapters/bigquery/relation.py
dbt/include/bigquery/__init__.py
dbt/include/bigquery/dbt_project.yml
dbt/include/bigquery/profile_template.yml
dbt/include/bigquery/macros/adapters.sql
dbt/include/bigquery/macros/catalog.sql
dbt/include/bigquery/macros/etc.sql
dbt/include/bigquery/macros/materializations/copy.sql
dbt/include/bigquery/macros/materializations/incremental.sql
dbt/include/bigquery/macros/materializations/seed.sql
dbt/include/bigquery/macros/materializations/snapshot.sql
dbt/include/bigquery/macros/materializations/table.sql
dbt/include/bigquery/macros/materializations/view.sql
dbt_bigquery_velocity.egg-info/PKG-INFO
dbt_bigquery_velocity.egg-info/SOURCES.txt
dbt_bigquery_velocity.egg-info/dependency_links.txt
dbt_bigquery_velocity.egg-info/not-zip-safe
dbt_bigquery_velocity.egg-info/requires.txt
dbt_bigquery_velocity.egg-info/top_level.txt