Metadata-Version: 2.1
Name: dbt-bigquery-velocity
Version: 1.1.0
Summary: The BigQuery adapter plugin for dbt
Home-page: https://github.com/Velocity-Engineering/dbt-bigquery-velocity
Author: Velocity
Author-email: info@dbtlabs.com
Classifier: Development Status :: 5 - Production/Stable
Classifier: License :: OSI Approved :: Apache Software License
Classifier: Operating System :: Microsoft :: Windows
Classifier: Operating System :: MacOS :: MacOS X
Classifier: Operating System :: POSIX :: Linux
Classifier: Programming Language :: Python :: 3.7
Classifier: Programming Language :: Python :: 3.8
Classifier: Programming Language :: Python :: 3.9
Requires-Python: >=3.7
License-File: LICENSE.md
